search/__init__.py
search/input.py
search/main.py
search/output.py
search/page.py
web-search/__init__.py
web-search/input.py
web-search/main.py
web-search/output.py
web-search/page.py
xsearch/__init__.py
xsearch/input.py
xsearch/main.py
xsearch/output.py
xsearch/page.py
xsearch-1.0.6.dist-info/METADATA
xsearch-1.0.6.dist-info/RECORD
xsearch-1.0.6.dist-info/WHEEL
xsearch-1.0.6.dist-info/top_level.txt
