Metadata-Version: 2.1
Name: xsearch
Version: 1.0.6
Summary: Search, export and analyse more efficiently
Home-page: https://github.com/YuqingXue/xsearch
Author: Yuqing Xue
Author-email: xueyuqing98@163.com
License: UNKNOWN
Platform: UNKNOWN
Classifier: Programming Language :: Python :: 3
Classifier: Operating System :: OS Independent
